chirp_64/__init__.py
chirp_64/__main__.py
chirp_64/audio_capture.py
chirp_64/config.py
chirp_64/continous_receiver.py
chirp_64/modem.py
chirp_64/plotter.py
chirp_64/py.typed
chirp_64/signal_processor.py
chirp_64-1.0.0.dist-info/METADATA
chirp_64-1.0.0.dist-info/WHEEL
chirp_64-1.0.0.dist-info/entry_points.txt
chirp_64-1.0.0.dist-info/RECORD
