Metadata-Version: 2.1
Name: chirp-64
Version: 1.0.0
Summary: Cross-correlation based digital mode reciever/simulator for amateur radios
Home-page: https://github.com/valibali/chirp-64
License: BIOS
Author: Valkony Balazs
Requires-Python: >=3.10,<4.0
Classifier: Development Status :: 4 - Beta
Classifier: Intended Audience :: Developers
Classifier: License :: Other/Proprietary License
Classifier: Operating System :: OS Independent
Classifier: Programming Language :: Python
Classifier: Programming Language :: Python :: 3
Classifier: Programming Language :: Python :: 3.10
Classifier: Programming Language :: Python :: 3.11
Classifier: Programming Language :: Python :: 3.12
Classifier: Programming Language :: Python :: 3.13
Classifier: Programming Language :: Python :: 3.7
Classifier: Programming Language :: Python :: 3.8
Classifier: Programming Language :: Python :: 3.9
Classifier: Topic :: Software Development :: Libraries :: Python Modules
Classifier: Typing :: Typed
Requires-Dist: matplotlib (>=3.9.2,<4.0.0)
Requires-Dist: numpy (>=2.1.3,<3.0.0)
Requires-Dist: pyaudio (>=0.2.14,<0.3.0)
Requires-Dist: scipy (>=1.14.1,<2.0.0)
Project-URL: Repository, https://github.com/valibali/chirp-64
